{
  "cards": [
    {
      "title": "Gilmore Girls",
      "directors": "Amy Sherman-Palladino",
      "stars": "8.2",
      "platform": "Netflix"
    },
    {
      "title": "Demon Slayer",
      "directors": "Haruo Sotozaki",
      "stars": "8.7",
      "platform": "Netflix"
    },
    {
      "title": "Squid Game",
      "directors": "Hwang Dong-hyuk",
      "stars": "8.0",
      "platform": "Netflix"
    },
    {
      "title": "FRIENDS",
      "directors": "David Crane & Marta Kauffman",
      "stars": "8.9",
      "platform": "Netflix"
    },
    {
      "title": "Doraemon",
      "directors": "Mitsuo Kaminashi",
      "stars": "8.3",
      "platform": "Hotstar"
    },
    {
      "title": "Farzi",
      "directors": "Raj & DK",
      "stars": "8.4",
      "platform": "Prime-Video"
    }
  ]
}
